logq/__init__.py
logq/admin.py
logq/apps.py
logq/async_logger.py
logq/cleanup_service.py
logq/handlers.py
logq/middleware.py
logq/models.py
logq/tests.py
logq/urls.py
logq/utils.py
logq/views.py
logq/management/__init__.py
logq/management/commands/__init__.py
logq/management/commands/clean_logs.py
logq/migrations/0001_initial.py
logq/migrations/0002_alter_logentry_function_alter_logentry_line_number_and_more.py
logq/migrations/__init__.py
djlogq-1.0.10.dist-info/METADATA
djlogq-1.0.10.dist-info/WHEEL
djlogq-1.0.10.dist-info/top_level.txt
djlogq-1.0.10.dist-info/RECORD
