Metadata-Version: 2.4
Name: djlogq
Version: 1.0.10
Summary: A robust and reusable Django app for asynchronous, thread-safe logging. Features include rich metadata capture, background log cleanup, configurable retention policies, admin interface, and REST API support for seamless log management.
Author-email: mess <mesnavunawa@gmail.com>
License: MIT
Project-URL: Homepage, https://github.com/Mesake94/djlogq
Project-URL: Downloads, https://pepy.tech/projects/djlogq
Requires-Python: >=3.8
Requires-Dist: Django
Requires-Dist: requests
Provides-Extra: dev
Requires-Dist: build==1.2.1; extra == "dev"
Requires-Dist: nox==2024.4.15; extra == "dev"
Requires-Dist: twine==5.1.1; extra == "dev"
